odoo/addons/stock_location_pending_move/README.rst
odoo/addons/stock_location_pending_move/__init__.py
odoo/addons/stock_location_pending_move/__manifest__.py
odoo/addons/stock_location_pending_move/i18n/it.po
odoo/addons/stock_location_pending_move/i18n/stock_location_pending_move.pot
odoo/addons/stock_location_pending_move/models/__init__.py
odoo/addons/stock_location_pending_move/models/stock_location.py
odoo/addons/stock_location_pending_move/readme/CONFIGURE.md
odoo/addons/stock_location_pending_move/readme/CONTEXT.md
odoo/addons/stock_location_pending_move/readme/CONTRIBUTORS.md
odoo/addons/stock_location_pending_move/readme/DESCRIPTION.md
odoo/addons/stock_location_pending_move/readme/USAGE.md
odoo/addons/stock_location_pending_move/static/description/icon.png
odoo/addons/stock_location_pending_move/static/description/index.html
odoo/addons/stock_location_pending_move/static/description/pending_moves.png
odoo/addons/stock_location_pending_move/static/description/pending_moves_detail.png
odoo/addons/stock_location_pending_move/tests/__init__.py
odoo/addons/stock_location_pending_move/tests/test_location_pending_move.py
odoo/addons/stock_location_pending_move/views/stock_location.xml
odoo_addon_stock_location_pending_move-18.0.1.0.0.3.dist-info/METADATA
odoo_addon_stock_location_pending_move-18.0.1.0.0.3.dist-info/WHEEL
odoo_addon_stock_location_pending_move-18.0.1.0.0.3.dist-info/top_level.txt
odoo_addon_stock_location_pending_move-18.0.1.0.0.3.dist-info/RECORD
